setup.py
duckapi/__init__.py
duckapi/asset.py
duckapi/client.py
duckapi/config.py
duckapi/exceptions.py
duckapi.egg-info/PKG-INFO
duckapi.egg-info/SOURCES.txt
duckapi.egg-info/dependency_links.txt
duckapi.egg-info/top_level.txt