Metadata-Version: 2.1
Name: duckapi
Version: 0.0.1
Summary: Async API wrapper for DuckAPI.
Home-page: https://github.com/Its-MatriX/duckapi-wrapper
Author: Its-MatriX; Lcvb-x
Keywords: api wrapper api-wrapper duck duck-api
Classifier: Development Status :: 5 - Production/Stable
Classifier: Programming Language :: Python :: 3
Classifier: Programming Language :: Python :: 3.8
Classifier: Programming Language :: Python :: 3.9
Classifier: Programming Language :: Python :: 3 :: Only
Classifier: Framework :: AsyncIO
